requake/__init__.py
requake/_version.py
requake/main.py
requake/catalog/__init__.py
requake/catalog/catalog.py
requake/catalog/print_catalog.py
requake/catalog/read_catalog.py
requake/catalog/read_catalog_from_csv.py
requake/catalog/read_catalog_from_fdsnws.py
requake/catalog/read_catalog_from_quakeml.py
requake/config/__init__.py
requake/config/config.py
requake/config/configspec.conf
requake/config/generic_printer.py
requake/config/parse_arguments.py
requake/config/rq_setup.py
requake/config/utils.py
requake/config/configobj/__init__.py
requake/config/configobj/_version.py
requake/config/configobj/validate.py
requake/families/__init__.py
requake/families/build_families.py
requake/families/build_templates.py
requake/families/families.py
requake/families/flag_family.py
requake/families/pairs.py
requake/families/print_families.py
requake/families/print_pairs.py
requake/formulas/__init__.py
requake/formulas/conversion.py
requake/formulas/moment.py
requake/formulas/slip.py
requake/plot/__init__.py
requake/plot/cached_tiler.py
requake/plot/map_families.py
requake/plot/map_tiles.py
requake/plot/plot_cumulative.py
requake/plot/plot_families.py
requake/plot/plot_pair.py
requake/plot/plot_timespans.py
requake/plot/plot_utils.py
requake/scan/__init__.py
requake/scan/scan_catalog.py
requake/scan/scan_templates.py
requake/waveforms/__init__.py
requake/waveforms/arrivals.py
requake/waveforms/station_metadata.py
requake/waveforms/waveforms.py
requake-0.6.dist-info/LICENSE.txt
requake-0.6.dist-info/METADATA
requake-0.6.dist-info/WHEEL
requake-0.6.dist-info/entry_points.txt
requake-0.6.dist-info/top_level.txt
requake-0.6.dist-info/RECORD
