Metadata-Version: 2.1
Name: requake
Version: 0.6
Summary: Repeating earthquakes search and analysis
Home-page: https://requake.seismicsource.org
Author: Claudio Satriano
Author-email: satriano@ipgp.fr
License: GNU General Public License v3 or later (GPLv3+)
Project-URL: Homepage, https://requake.seismicsource.org
Project-URL: Source, https://github.com/SeismicSource/requake
Project-URL: Documentation, https://requake.readthedocs.io
Platform: OS Independent
Classifier: Development Status :: 4 - Beta
Classifier: Environment :: Console
Classifier: Intended Audience :: Science/Research
Classifier: License :: OSI Approved :: GNU General Public License v3 or later (GPLv3+)
Classifier: Operating System :: OS Independent
Classifier: Programming Language :: Python
Classifier: Programming Language :: Python :: 3
Classifier: Programming Language :: Python :: 3.7
Classifier: Programming Language :: Python :: 3.8
Classifier: Programming Language :: Python :: 3.9
Classifier: Programming Language :: Python :: 3.10
Classifier: Programming Language :: Python :: 3.11
Classifier: Topic :: Scientific/Engineering
Classifier: Topic :: Scientific/Engineering :: Physics
Requires-Python: >3.7
License-File: LICENSE.txt
Requires-Dist: scipy >=1.5.0
Requires-Dist: obspy >=1.2.0
Requires-Dist: argcomplete
Requires-Dist: tqdm
Requires-Dist: tabulate
